.coveragerc
.travis.yml
AUTHORS.rst
CHANGES.rst
LICENSE.txt
README.rst
requirements.txt
setup.cfg
setup.py
test-requirements.txt
tox.ini
ISA.egg-info/PKG-INFO
ISA.egg-info/SOURCES.txt
ISA.egg-info/dependency_links.txt
ISA.egg-info/entry_points.txt
ISA.egg-info/not-zip-safe
ISA.egg-info/requires.txt
ISA.egg-info/top_level.txt
docs/Makefile
docs/authors.rst
docs/changes.rst
docs/conf.py
docs/index.rst
docs/ini.rst
docs/install.rst
docs/license.rst
docs/plugins.rst
docs/usage.rst
docs/_static/.gitignore
isa/__init__.py
isa/exceptions.py
isa/ini.py
isa/monitor.py
isa/output.py
isa/plugin.py
isa/plugin_collectl.py
isa/plugin_free.py
isa/plugin_iostat.py
isa/runner.py
isa/server.py
isa/util.py
tests/test_collectl.py
tests/test_free.py
tests/test_ini.py
tests/test_iostat.py
tests/test_output.py
tests/travis_install.sh