Metadata-Version: 1.1
Name: ISA
Version: 1.2.4
Summary: ISA (Independent Statistics Aggregator) collects node statistics for a cluster of nodes.
Home-page: https://www.data-blogger.com/
Author: Kevin Jacobs
Author-email: kevin91nl@gmail.com
License: MIT
Platform: UNKNOWN
Classifier: Development Status :: 4 - Beta
Classifier: Programming Language :: Python
